pyroglyph/__init__.py
pyroglyph/exceptions.py
pyroglyph-0.1.0.dist-info/LICENSE
pyroglyph-0.1.0.dist-info/METADATA
pyroglyph-0.1.0.dist-info/WHEEL
pyroglyph-0.1.0.dist-info/RECORD
