Metadata-Version: 2.1
Name: pyroglyph
Version: 0.1.0
Summary: A simple library for building real-time text-based UIs
Home-page: https://github.com/ChrisTimperley/pyroglyph
License: Apache-2.0
Keywords: cli,curses,ui,terminal
Author: Chris Timperley
Author-email: ctimperley@cmu.edu
Requires-Python: >=3.9
Classifier: Intended Audience :: Developers
Classifier: License :: OSI Approved :: Apache Software License
Classifier: Programming Language :: Python :: 3
Classifier: Programming Language :: Python :: 3.9
Classifier: Programming Language :: Python :: 3.10
Classifier: Programming Language :: Python :: 3.11
Classifier: Programming Language :: Python :: 3.12
Requires-Dist: blessed (>=1.18.0)
Project-URL: Repository, https://github.com/ChrisTimperley/pyroglyph
